pyclassifier/__init__.py
pyclassifier/classifier.py
pyclassifier-0.0.3.dist-info/LICENSE
pyclassifier-0.0.3.dist-info/METADATA
pyclassifier-0.0.3.dist-info/WHEEL
pyclassifier-0.0.3.dist-info/top_level.txt
pyclassifier-0.0.3.dist-info/RECORD
