Metadata-Version: 2.1
Name: pyclassifier
Version: 0.0.3
Summary: A module to create classes out of dictionaries
Home-page: https://github.com/rahmansharifi/pyclassifier
Author: Rahman Sharifi
Author-email: sharifi.rahman.4651@gmail.com
License: UNKNOWN
Project-URL: Bug Tracker, https://github.com/rahmansharifi/pyclassifier/issues
Platform: UNKNOWN
Classifier: Programming Language :: Python :: 3
Classifier: License :: OSI Approved :: MIT License
Classifier: Operating System :: OS Independent
Requires-Python: >=3.6
License-File: LICENSE
